<root annotationID="0" passageID="newstest2014-fren-src.en-skipline_1291">
  <attributes />
  <extra format="text" />
  <layer layerID="0">
    <attributes />
    <extra doc="[[[12346995674149584082, 10382539506755952630, 13927759927860985106, 99, 0, 2, 403, 2, 12204527652707022206, 4690420944186131903, 12346995674149584082], [1995909169258310477, 1995909169258310477, 15267657372422890137, 89, 0, 2, 427, 1, 13110060611322374290, 15369245168918225700, 2661093235354845946], [12099349157015164054, 15580274710609099813, 3822385049556375858, 99, 0, 2, 8206900633647566924, 0, 13110060611322374290, 646772771845179972, 7886043512438591911], [3791531372978436496, 3791531372978436496, 5595707737748328492, 93, 0, 2, 402, 1, 4370460163704169311, 15369245168918225700, 3791531372978436496], [99974891130002844, 99974891130002844, 14200088355797579614, 99, 0, 2, 446, -2, 13110060611322374290, 8861071527689086543, 3743965404940708265], [15275761157247972012, 1153941636839804325, 15794550382381185553, 95, 0, 2, 7037928807040764755, 1, 17096342708991983284, 3209455878668673793, 15275761157247972012], [7975802927099504321, null, 15794550382381185553, 95, 378, 3, 413, -2, 16072095006890171862, 3209455878668673793, 10438648983378644488], [8205403955989537350, 8205403955989537350, 12646065887601541794, 96, 0, 2, 442, -5, 8205403955989537350, 8205403955989537350, 8205403955989537350]]]" />
    <node ID="0.1" type="Word">
      <attributes paragraph="1" paragraph_position="1" text="Is" />
    </node>
    <node ID="0.2" type="Word">
      <attributes paragraph="1" paragraph_position="2" text="this" />
    </node>
    <node ID="0.3" type="Word">
      <attributes paragraph="1" paragraph_position="3" text="meant" />
    </node>
    <node ID="0.4" type="Word">
      <attributes paragraph="1" paragraph_position="4" text="to" />
    </node>
    <node ID="0.5" type="Word">
      <attributes paragraph="1" paragraph_position="5" text="please" />
    </node>
    <node ID="0.6" type="Word">
      <attributes paragraph="1" paragraph_position="6" text="Mr." />
    </node>
    <node ID="0.7" type="Word">
      <attributes paragraph="1" paragraph_position="7" text="Montebourg" />
    </node>
    <node ID="0.8" type="Punctuation">
      <attributes paragraph="1" paragraph_position="8" text="?" />
    </node>
  </layer>
  <layer layerID="1">
    <attributes />
    <node ID="1.1" type="FN">
      <attributes />
      <edge toID="1.2" type="H">
        <attributes />
      </edge>
    </node>
    <node ID="1.2" type="FN">
      <attributes />
      <edge toID="1.3" type="R">
        <attributes />
      </edge>
      <edge toID="1.4" type="A">
        <attributes />
      </edge>
    </node>
    <node ID="1.3" type="FN">
      <attributes />
      <edge toID="0.1" type="Terminal">
        <attributes />
      </edge>
      <edge toID="0.2" type="Terminal">
        <attributes />
      </edge>
      <edge toID="0.3" type="Terminal">
        <attributes />
      </edge>
    </node>
    <node ID="1.4" type="FN">
      <attributes />
      <edge toID="1.5" type="F">
        <attributes />
      </edge>
      <edge toID="1.6" type="P">
        <attributes />
      </edge>
      <edge toID="1.7" type="A">
        <attributes />
      </edge>
    </node>
    <node ID="1.5" type="FN">
      <attributes />
      <edge toID="0.4" type="Terminal">
        <attributes />
      </edge>
    </node>
    <node ID="1.6" type="FN">
      <attributes />
      <edge toID="0.5" type="Terminal">
        <attributes />
      </edge>
    </node>
    <node ID="1.7" type="FN">
      <attributes />
      <edge toID="1.8" type="C">
        <attributes />
      </edge>
      <edge toID="1.9" type="U">
        <attributes />
      </edge>
    </node>
    <node ID="1.8" type="FN">
      <attributes />
      <edge toID="0.6" type="Terminal">
        <attributes />
      </edge>
      <edge toID="0.7" type="Terminal">
        <attributes />
      </edge>
    </node>
    <node ID="1.9" type="PNCT">
      <attributes />
      <edge toID="0.8" type="Terminal">
        <attributes />
      </edge>
    </node>
  </layer>
</root>
